jerkup/__init__.py
jerkup/__main__.py
jerkup/configuration.py
jerkup/formatter.py
jerkup/iso8601.py
jerkup/messages.py
jerkup/py.typed
jerkup/session.py
jerkup/uploader.py
jerkup-2.2.0.dist-info/METADATA
jerkup-2.2.0.dist-info/WHEEL
jerkup-2.2.0.dist-info/entry_points.txt
jerkup-2.2.0.dist-info/RECORD
