Metadata-Version: 2.4
Name: jerkup
Version: 2.2.0
Summary: Hamster Uploader
License: MIT
Author: deadmaster
Author-email: deadmaster@noreply.codeberg.org
Requires-Python: >=3.13,<4.0
Classifier: License :: OSI Approved :: MIT License
Classifier: Programming Language :: Python :: 3
Classifier: Programming Language :: Python :: 3.13
Classifier: Programming Language :: Python :: 3.14
Classifier: Topic :: Internet :: WWW/HTTP
Requires-Dist: msgspec (>=0.20.0,<0.21.0)
Requires-Dist: platformdirs (>=4.5.1,<5.0.0)
Requires-Dist: requests (>=2.32.5,<3.0.0)
Requires-Dist: requests-toolbelt (>=1.0.0,<2.0.0)
Project-URL: Repository, https://codeberg.org/deadmaster/jerkup
